apod.py
apod.py-0.0.1.dist-info/LICENSE
apod.py-0.0.1.dist-info/METADATA
apod.py-0.0.1.dist-info/WHEEL
apod.py-0.0.1.dist-info/top_level.txt
apod.py-0.0.1.dist-info/RECORD
